deliverymatch/__init__.py
deliverymatch/client.py
deliverymatch/errors.py
deliverymatch/py.typed
deliverymatch/types.py
deliverymatch/api/__init__.py
deliverymatch/api/default/__init__.py
deliverymatch/api/default/add_document.py
deliverymatch/api/default/close_linehaul.py
deliverymatch/api/default/delete_document.py
deliverymatch/api/default/download_attachment.py
deliverymatch/api/default/get_design.py
deliverymatch/api/default/get_document.py
deliverymatch/api/default/get_label.py
deliverymatch/api/default/get_linehauls.py
deliverymatch/api/default/get_locations.py
deliverymatch/api/default/get_services.py
deliverymatch/api/default/get_shipment.py
deliverymatch/api/default/get_shipments.py
deliverymatch/api/default/get_status.py
deliverymatch/api/default/insert_shipment.py
deliverymatch/api/default/insert_shipments.py
deliverymatch/api/default/push_status_events.py
deliverymatch/api/default/retrieve_all_document_ids.py
deliverymatch/api/default/test_api_connection.py
deliverymatch/api/default/update_document.py
deliverymatch/api/default/update_routes.py
deliverymatch/api/default/update_shipment.py
deliverymatch/api/default/update_shipment_method.py
deliverymatch/models/__init__.py
deliverymatch/models/add_document_body.py
deliverymatch/models/add_document_response_201.py
deliverymatch/models/add_document_response_201_document_type.py
deliverymatch/models/add_document_response_201_file_type.py
deliverymatch/models/address.py
deliverymatch/models/client.py
deliverymatch/models/client_action.py
deliverymatch/models/client_method.py
deliverymatch/models/close_linehaul_body.py
deliverymatch/models/close_linehaul_body_address.py
deliverymatch/models/close_linehaul_response_200.py
deliverymatch/models/contact.py
deliverymatch/models/customer.py
deliverymatch/models/customer_customs_info.py
deliverymatch/models/document.py
deliverymatch/models/document_document_type.py
deliverymatch/models/document_file_type.py
deliverymatch/models/download_attachment_body.py
deliverymatch_python-0.1.0.dist-info/METADATA
deliverymatch_python-0.1.0.dist-info/WHEEL
deliverymatch_python-0.1.0.dist-info/RECORD
