Metadata-Version: 2.4
Name: deliverymatch-python
Version: 0.1.0
Summary: Python client for DeliveryMatch API
Requires-Python: >=3.10
Requires-Dist: attrs>=21.3.0
Requires-Dist: httpx>=0.20.0
Requires-Dist: python-dateutil>=2.8.0
